certbot_dns_safedns/__init__.py
certbot_dns_safedns/dns_safedns.py
certbot_dns_safedns/dns_safedns_test.py
certbot_dns_safedns-0.1.49.data/data/VERSION
certbot_dns_safedns-0.1.49.data/data/requirements.txt
certbot_dns_safedns-0.1.49.data/data/setup.py
certbot_dns_safedns-0.1.49.dist-info/LICENSE.txt
certbot_dns_safedns-0.1.49.dist-info/METADATA
certbot_dns_safedns-0.1.49.dist-info/WHEEL
certbot_dns_safedns-0.1.49.dist-info/entry_points.txt
certbot_dns_safedns-0.1.49.dist-info/top_level.txt
certbot_dns_safedns-0.1.49.dist-info/RECORD
